excel_db/__init__.py
excel_db/run.py
excel_db/sql.py
excel_db-1.0.dist-info/METADATA
excel_db-1.0.dist-info/RECORD
excel_db-1.0.dist-info/WHEEL
excel_db-1.0.dist-info/top_level.txt
